src/dRun.py
am4problemFinder-0.0.1.dist-info/LICENSE
am4problemFinder-0.0.1.dist-info/METADATA
am4problemFinder-0.0.1.dist-info/WHEEL
am4problemFinder-0.0.1.dist-info/entry_points.txt
am4problemFinder-0.0.1.dist-info/top_level.txt
am4problemFinder-0.0.1.dist-info/RECORD
