Metadata-Version: 2.1
Name: am4problemFinder
Version: 0.0.1
Summary: A tool to help you find issues of your flights in Airline Manager 4.
Home-page: https://github.com/cathaypacific8747/am4problemfinder/
Author: Cathay Express
Author-email: cathayexpress4@gmail.com
License: GNU AGPL-3.0
Platform: UNKNOWN
Classifier: Development Status :: 4 - Beta
Classifier: Programming Language :: Python :: 3
Requires-Dist: lxml
Requires-Dist: colorama
Requires-Dist: prettytable
Requires-Dist: urllib3
Requires-Dist: bs4
